Metadata-Version: 1.0
Name: mp-test
Version: 1.0
Summary: mp-test
Home-page: UNKNOWN
Author: rodbate
Author-email: rodbatejss@gmail.com
License: UNKNOWN
Platform: UNKNOWN
